Metadata-Version: 2.4
Name: pyfhiaims
Version: 0.0.9
Summary: An FHI-aims official Python package
Author-email: Thomas Purcell <purcell@fhi-berlin.mpg.de>, Andrei Sobolev <sobolev@ms1p.org>
Maintainer-email: Thomas Purcell <purcell@fhi-berlin.mpg.de>, Andrei Sobolev <sobolev@ms1p.org>
License: MIT
Project-URL: repository, https://gitlab.com/FHI-aims-club/pyfhiaims/
Keywords: electronic structure,FHI-aims
Classifier: Programming Language :: Python :: 3.10
Classifier: Programming Language :: Python :: 3.11
Classifier: Programming Language :: Python :: 3.12
Requires-Python: >=3.10
License-File: LICENSE
Requires-Dist: numpy
Requires-Dist: scipy>=1.1.1
Requires-Dist: monty>=2024.10.21
Requires-Dist: pyyaml
Provides-Extra: tests
Requires-Dist: pyyaml; extra == "tests"
Requires-Dist: pytest>=6.0; extra == "tests"
Requires-Dist: pytest-xdist>=1.31; extra == "tests"
Requires-Dist: pytest-cov>=2.8; extra == "tests"
Provides-Extra: dev
Requires-Dist: pre-commit>=2.12.1; extra == "dev"
Dynamic: license-file
